passosh/__init__.py
passosh/fields.py
passosh/pesso.py
passosh/signature.py
passosh/zip.py
passosh-0.0.4.dist-info/METADATA
passosh-0.0.4.dist-info/WHEEL
passosh-0.0.4.dist-info/licenses/LICENSE
passosh-0.0.4.dist-info/RECORD
